{
    "sect": {
        "camarilla": "wod.bio.vampire.camarilla",
        "sabbat": "wod.bio.vampire.sabbat",
        "anarch": "wod.bio.vampire.anarch",
        "independent": "wod.bio.vampire.independent",
        "blackhand": "wod.bio.vampire.blackhand",
        "inconnu": "wod.bio.vampire.inconnu"
    },
    "clan": {
        "caitiff": "wod.bio.vampire.caitiff",
        "assamite": "wod.bio.vampire.assamite",
        "brujah": "wod.bio.vampire.brujah",
        "set": "wod.bio.vampire.set",
        "gangrel": "wod.bio.vampire.gangrel",
        "giovanni": "wod.bio.vampire.giovanni",
        "lasombra": "wod.bio.vampire.lasombra",
        "malkavian": "wod.bio.vampire.malkavian",
        "nosferatu": "wod.bio.vampire.nosferatu",
        "ravnos": "wod.bio.vampire.ravnos",
        "toreador": "wod.bio.vampire.toreador",
        "tremere": "wod.bio.vampire.tremere",
        "tzimisce": "wod.bio.vampire.tzimisce",
        "ventrue": "wod.bio.vampire.ventrue"
    },
    "path": {
        "humanity": "wod.advantages.path.humanity",
        "blood": "wod.advantages.path.blood",
        "caine": "wod.advantages.path.caine",
        "cathari": "wod.advantages.path.cathari",
        "feralheart": "wod.advantages.path.feralheart",
        "accord": "wod.advantages.path.accord",
        "lilith": "wod.advantages.path.lilith",
        "metamorphosis": "wod.advantages.path.metamorphosis",
        "night": "wod.advantages.path.night",
        "paradox": "wod.advantages.path.paradox",
        "innervoice": "wod.advantages.path.innervoice",
        "typhon": "wod.advantages.path.typhon"
    },
    "tribe": {
        "blackfuries": "wod.bio.werewolf.blackfuries",
        "bonegnawer": "wod.bio.werewolf.bonegnawer",
        "childrenofgaia": "wod.bio.werewolf.childrenofgaia",
        "fianna": "wod.bio.werewolf.fianna",
        "getoffenris": "wod.bio.werewolf.getoffenris",
        "glasswalker": "wod.bio.werewolf.glasswalker",
        "redtalon": "wod.bio.werewolf.redtalon",
        "shadowlord": "wod.bio.werewolf.shadowlord",
        "silentstrider": "wod.bio.werewolf.silentstrider",
        "silverfang": "wod.bio.werewolf.silverfang",
        "stargazer": "wod.bio.werewolf.stargazer",
        "uktena": "wod.bio.werewolf.uktena",
        "wendigo": "wod.bio.werewolf.wendigo",
        "blackspiraldancer": "wod.bio.werewolf.blackspiraldancer",
        "skindancer": "wod.bio.werewolf.skindancer"
    },
    "affiliation": {
        "tradition": "wod.bio.mage.tradition",
        "technocracy": "wod.bio.mage.technocracy",
        "disparate": "wod.bio.mage.disparate",
        "fallen": "wod.bio.mage.fallen",
        "mad": "wod.bio.mage.mad"
    },
    "magesect": {
        "tradition": {
            "akashic": "wod.bio.mage.akashic",
            "chorus": "wod.bio.mage.chorus",
            "ecstasy": "wod.bio.mage.ecstasy",
            "speakers": "wod.bio.mage.speakers",
            "euthanatos": "wod.bio.mage.euthanatos",
            "hermes": "wod.bio.mage.hermes",
            "ether": "wod.bio.mage.ether",
            "verbena": "wod.bio.mage.verbena",
            "adepts": "wod.bio.mage.adepts"
        },
        "technocracy": {
            "iterationx": "wod.bio.mage.iterationx",
            "nwo": "wod.bio.mage.nwo",
            "progenitors": "wod.bio.mage.progenitors",
            "syndicate": "wod.bio.mage.syndicate",
            "engineers": "wod.bio.mage.engineers"
        },
        "disparate": {
            "batin": "wod.bio.mage.batin",
            "bataa": "wod.bio.mage.bataa",
            "children": "wod.bio.mage.children",
            "hollow": "wod.bio.mage.hollow",
            "kopa": "wod.bio.mage.kopa",
            "ngoma": "wod.bio.mage.ngoma",
            "orphans": "wod.bio.mage.orphans",
            "hippolyta": "wod.bio.mage.hippolyta",
            "taftani": "wod.bio.mage.taftani",
            "templar": "wod.bio.mage.templar",
            "wulung": "wod.bio.mage.wulung"
        },
        "fallen": {
            "nephandi": "wod.bio.mage.nephandi"
        },
        "mad": {
            "marauder": "wod.bio.mage.marauder"
        }
    },    
    "kith": {
        "boggans": "wod.bio.changeling.boggans",
        "clurichaun": "wod.bio.changeling.clurichaun",
        "eshu": "wod.bio.changeling.eshu",
        "nockers": "wod.bio.changeling.nockers",
        "piskies": "wod.bio.changeling.piskies",
        "pooka": "wod.bio.changeling.pooka",
        "redcap": "wod.bio.changeling.redcap",
        "satyrs": "wod.bio.changeling.satyrs",
        "selkies": "wod.bio.changeling.selkies",
        "sidhe": "wod.bio.changeling.sidhe",
        "sluagh": "wod.bio.changeling.sluagh",
        "troll": "wod.bio.changeling.troll"
    }
}